{"metadata": {"dbt_schema_version": "https://schemas.getdbt.com/dbt/run-results/v6.json", "dbt_version": "1.9.2", "generated_at": "2025-02-11T08:49:17.805542Z", "invocation_id": "00848dc9-ad72-4c66-b5f1-55c3d167bfb5", "env": {}}, "results": [{"status": "pass", "timing": [{"name": "compile", "started_at": "2025-02-11T08:49:17.598627Z", "completed_at": "2025-02-11T08:49:17.609170Z"}, {"name": "execute", "started_at": "2025-02-11T08:49:17.609462Z", "completed_at": "2025-02-11T08:49:17.629640Z"}], "thread_id": "Thread-1 (worker)", "execution_time": 0.033303022384643555, "adapter_response": {"_message": "OK"}, "message": null, "failures": 0, "unique_id": "test.my_star_schema_project.not_null_dim_customers_customer_city.f59e32635d", "compiled": true, "compiled_code": "\n    \n    \n\n\n\nselect customer_city\nfrom \"duckdb\".\"main\".\"dim_customers\"\nwhere customer_city is null\n\n\n", "relation_name": null, "batch_results": null}, {"status": "pass", "timing": [{"name": "compile", "started_at": "2025-02-11T08:49:17.632984Z", "completed_at": "2025-02-11T08:49:17.635560Z"}, {"name": "execute", "started_at": "2025-02-11T08:49:17.635767Z", "completed_at": "2025-02-11T08:49:17.646415Z"}], "thread_id": "Thread-1 (worker)", "execution_time": 0.01567387580871582, "adapter_response": {"_message": "OK"}, "message": null, "failures": 0, "unique_id": "test.my_star_schema_project.not_null_dim_customers_customer_id.dd91cd1c8d", "compiled": true, "compiled_code": "\n    \n    \n\n\n\nselect customer_id\nfrom \"duckdb\".\"main\".\"dim_customers\"\nwhere customer_id is null\n\n\n", "relation_name": null, "batch_results": null}, {"status": "pass", "timing": [{"name": "compile", "started_at": "2025-02-11T08:49:17.649805Z", "completed_at": "2025-02-11T08:49:17.652406Z"}, {"name": "execute", "started_at": "2025-02-11T08:49:17.652609Z", "completed_at": "2025-02-11T08:49:17.662240Z"}], "thread_id": "Thread-1 (worker)", "execution_time": 0.014400005340576172, "adapter_response": {"_message": "OK"}, "message": null, "failures": 0, "unique_id": "test.my_star_schema_project.not_null_dim_customers_customer_name.c8ab2d704d", "compiled": true, "compiled_code": "\n    \n    \n\n\n\nselect customer_name\nfrom \"duckdb\".\"main\".\"dim_customers\"\nwhere customer_name is null\n\n\n", "relation_name": null, "batch_results": null}, {"status": "pass", "timing": [{"name": "compile", "started_at": "2025-02-11T08:49:17.665304Z", "completed_at": "2025-02-11T08:49:17.668468Z"}, {"name": "execute", "started_at": "2025-02-11T08:49:17.668680Z", "completed_at": "2025-02-11T08:49:17.679074Z"}], "thread_id": "Thread-1 (worker)", "execution_time": 0.015962839126586914, "adapter_response": {"_message": "OK"}, "message": null, "failures": 0, "unique_id": "test.my_star_schema_project.not_null_dim_customers_customer_state.7c7083b6aa", "compiled": true, "compiled_code": "\n    \n    \n\n\n\nselect customer_state\nfrom \"duckdb\".\"main\".\"dim_customers\"\nwhere customer_state is null\n\n\n", "relation_name": null, "batch_results": null}, {"status": "pass", "timing": [{"name": "compile", "started_at": "2025-02-11T08:49:17.682430Z", "completed_at": "2025-02-11T08:49:17.685194Z"}, {"name": "execute", "started_at": "2025-02-11T08:49:17.685410Z", "completed_at": "2025-02-11T08:49:17.698885Z"}], "thread_id": "Thread-1 (worker)", "execution_time": 0.018577098846435547, "adapter_response": {"_message": "OK"}, "message": null, "failures": 0, "unique_id": "test.my_star_schema_project.not_null_dim_products_price.93519fc0ed", "compiled": true, "compiled_code": "\n    \n    \n\n\n\nselect price\nfrom \"duckdb\".\"main\".\"dim_products\"\nwhere price is null\n\n\n", "relation_name": null, "batch_results": null}, {"status": "pass", "timing": [{"name": "compile", "started_at": "2025-02-11T08:49:17.702018Z", "completed_at": "2025-02-11T08:49:17.705989Z"}, {"name": "execute", "started_at": "2025-02-11T08:49:17.706223Z", "completed_at": "2025-02-11T08:49:17.718075Z"}], "thread_id": "Thread-1 (worker)", "execution_time": 0.018143892288208008, "adapter_response": {"_message": "OK"}, "message": null, "failures": 0, "unique_id": "test.my_star_schema_project.not_null_dim_products_product_category.069796c541", "compiled": true, "compiled_code": "\n    \n    \n\n\n\nselect product_category\nfrom \"duckdb\".\"main\".\"dim_products\"\nwhere product_category is null\n\n\n", "relation_name": null, "batch_results": null}, {"status": "pass", "timing": [{"name": "compile", "started_at": "2025-02-11T08:49:17.721806Z", "completed_at": "2025-02-11T08:49:17.724853Z"}, {"name": "execute", "started_at": "2025-02-11T08:49:17.725068Z", "completed_at": "2025-02-11T08:49:17.735656Z"}], "thread_id": "Thread-1 (worker)", "execution_time": 0.016275882720947266, "adapter_response": {"_message": "OK"}, "message": null, "failures": 0, "unique_id": "test.my_star_schema_project.not_null_dim_products_product_id.c8aba288d1", "compiled": true, "compiled_code": "\n    \n    \n\n\n\nselect product_id\nfrom \"duckdb\".\"main\".\"dim_products\"\nwhere product_id is null\n\n\n", "relation_name": null, "batch_results": null}, {"status": "pass", "timing": [{"name": "compile", "started_at": "2025-02-11T08:49:17.739215Z", "completed_at": "2025-02-11T08:49:17.742161Z"}, {"name": "execute", "started_at": "2025-02-11T08:49:17.742376Z", "completed_at": "2025-02-11T08:49:17.752468Z"}], "thread_id": "Thread-1 (worker)", "execution_time": 0.015752792358398438, "adapter_response": {"_message": "OK"}, "message": null, "failures": 0, "unique_id": "test.my_star_schema_project.not_null_dim_products_product_name.991aec73f3", "compiled": true, "compiled_code": "\n    \n    \n\n\n\nselect product_name\nfrom \"duckdb\".\"main\".\"dim_products\"\nwhere product_name is null\n\n\n", "relation_name": null, "batch_results": null}, {"status": "pass", "timing": [{"name": "compile", "started_at": "2025-02-11T08:49:17.756231Z", "completed_at": "2025-02-11T08:49:17.760686Z"}, {"name": "execute", "started_at": "2025-02-11T08:49:17.761171Z", "completed_at": "2025-02-11T08:49:17.775709Z"}], "thread_id": "Thread-1 (worker)", "execution_time": 0.021620988845825195, "adapter_response": {"_message": "OK"}, "message": null, "failures": 0, "unique_id": "test.my_star_schema_project.unique_dim_customers_customer_id.15c9f1e2fd", "compiled": true, "compiled_code": "\n    \n    \n\nselect\n    customer_id as unique_field,\n    count(*) as n_records\n\nfrom \"duckdb\".\"main\".\"dim_customers\"\nwhere customer_id is not null\ngroup by customer_id\nhaving count(*) > 1\n\n\n", "relation_name": null, "batch_results": null}, {"status": "pass", "timing": [{"name": "compile", "started_at": "2025-02-11T08:49:17.778953Z", "completed_at": "2025-02-11T08:49:17.782017Z"}, {"name": "execute", "started_at": "2025-02-11T08:49:17.782245Z", "completed_at": "2025-02-11T08:49:17.793108Z"}], "thread_id": "Thread-1 (worker)", "execution_time": 0.016297101974487305, "adapter_response": {"_message": "OK"}, "message": null, "failures": 0, "unique_id": "test.my_star_schema_project.unique_dim_products_product_id.ef7b2a9985", "compiled": true, "compiled_code": "\n    \n    \n\nselect\n    product_id as unique_field,\n    count(*) as n_records\n\nfrom \"duckdb\".\"main\".\"dim_products\"\nwhere product_id is not null\ngroup by product_id\nhaving count(*) > 1\n\n\n", "relation_name": null, "batch_results": null}], "elapsed_time": 0.34228992462158203, "args": {"indirect_selection": "eager", "introspect": true, "partial_parse_file_diff": true, "log_path": "/Users/takeshiiijima/github/duckdb-dbt/logs", "warn_error_options": {"include": [], "exclude": []}, "log_level": "info", "require_batched_execution_for_custom_microbatch_strategy": false, "require_explicit_package_overrides_for_builtin_materializations": true, "require_resource_names_without_spaces": false, "printer_width": 80, "require_yaml_configuration_for_mf_time_spines": false, "strict_mode": false, "macro_debugging": false, "log_format_file": "debug", "resource_types": [], "profiles_dir": "/Users/takeshiiijima/github/duckdb-dbt", "source_freshness_run_project_hooks": false, "quiet": false, "project_dir": "/Users/takeshiiijima/github/duckdb-dbt", "state_modified_compare_vars": false, "defer": false, "cache_selected_only": false, "skip_nodes_if_on_run_start_fails": false, "favor_state": false, "print": true, "partial_parse": true, "log_file_max_bytes": 10485760, "invocation_command": "dbt test", "select": [], "show_resource_report": false, "send_anonymous_usage_stats": true, "require_nested_cumulative_type_params": false, "state_modified_compare_more_unrendered_values": false, "write_json": true, "which": "test", "version_check": true, "populate_cache": true, "exclude": [], "log_format": "default", "use_colors_file": true, "exclude_resource_types": [], "vars": {}, "log_level_file": "debug", "static_parser": true, "use_colors": true}}